path/__init__.py
path/__init__.pyi
path/classes.py
path/classes.pyi
path/masks.py
path/matchers.py
path/matchers.pyi
path/py.typed
path/compat/py38.py
path-16.16.0.dist-info/LICENSE
path-16.16.0.dist-info/METADATA
path-16.16.0.dist-info/WHEEL
path-16.16.0.dist-info/top_level.txt
path-16.16.0.dist-info/RECORD
