Metadata-Version: 2.1
Name: path
Version: 16.16.0
Summary: A module wrapper for os.path
Author-email: Jason Orendorff <jason.orendorff@gmail.com>
Maintainer-email: "Jason R. Coombs" <jaraco@jaraco.com>
Project-URL: Source, https://github.com/jaraco/path
Classifier: Development Status :: 5 - Production/Stable
Classifier: Intended Audience :: Developers
Classifier: License :: OSI Approved :: MIT License
Classifier: Programming Language :: Python :: 3
Classifier: Programming Language :: Python :: 3 :: Only
Classifier: Operating System :: OS Independent
Classifier: Topic :: Software Development :: Libraries :: Python Modules
Requires-Python: >=3.8
License-File: LICENSE
Provides-Extra: test
Requires-Dist: pytest!=8.1.*,>=6; extra == "test"
Requires-Dist: pytest-checkdocs>=2.4; extra == "test"
Requires-Dist: pytest-cov; extra == "test"
Requires-Dist: pytest-mypy; extra == "test"
Requires-Dist: pytest-enabler>=2.2; extra == "test"
Requires-Dist: pytest-ruff>=0.2.1; sys_platform != "cygwin" and extra == "test"
Requires-Dist: appdirs; extra == "test"
Requires-Dist: packaging; extra == "test"
Requires-Dist: pywin32; (platform_system == "Windows" and python_version < "3.12") and extra == "test"
Requires-Dist: more_itertools; extra == "test"
Requires-Dist: pygments; extra == "test"
Provides-Extra: doc
Requires-Dist: sphinx>=3.5; extra == "doc"
Requires-Dist: jaraco.packaging>=9.3; extra == "doc"
Requires-Dist: rst.linker>=1.9; extra == "doc"
Requires-Dist: furo; extra == "doc"
Requires-Dist: sphinx-lint; extra == "doc"
Requires-Dist: jaraco.tidelift>=1.4; extra == "doc"
